omnihost/__init__.py
omnihost/__main__.py
omnihost/config_handler.py
omnihost/gemtext_parser.py
omnihost/html_converter.py
omnihost/omniconverter.py
omnihost/version.py
omnihost-0.4.0.dist-info/entry_points.txt
omnihost-0.4.0.dist-info/LICENSE.txt
omnihost-0.4.0.dist-info/WHEEL
omnihost-0.4.0.dist-info/METADATA
omnihost-0.4.0.dist-info/RECORD
