Metadata-Version: 2.1
Name: omnihost
Version: 0.4.0
Summary: Easily convert native Gemini (gemtext markup) files into html and gophermaps for trihosting
Home-page: https://github.com/b-src/omnihost
License: MIT
Author: Brett Gleason
Author-email: brettmgleason@gmail.com
Requires-Python: >=3.10,<4.0
Classifier: Development Status :: 3 - Alpha
Classifier: Environment :: Console
Classifier: Intended Audience :: End Users/Desktop
Classifier: License :: OSI Approved :: MIT License
Classifier: Operating System :: POSIX :: Linux
Classifier: Programming Language :: Python :: 3
Classifier: Programming Language :: Python :: 3 :: Only
Classifier: Programming Language :: Python :: 3.10
Classifier: Topic :: Internet
Project-URL: Repository, https://github.com/b-src/omnihost
